{
    "训练室任务": {
        "next": [
            "偶像训练"
        ],
        "interrupt": [
            "训练室_修正者",
            "进入训练室",
            "训练室_菜单",
            "进入游园街_训练室",
            "关闭待机页面"
        ]
    },
    "偶像训练": {
        "recognition": {
            "type": "OCR",
            "param": {
                "roi": [
                    756,
                    543,
                    127,
                    34
                ],
                "expected": [
                    "今日",
                    "培养",
                    "次数"
                ]
            }
        },
        "action": {
            "type": "Custom",
            "param": {
                "custom_action": "IdolTrainingMainProcess",
                "custom_action_param": {
                    "config_path": "custom_task_config\\idol_training",
                    "training_plan": {
                        "names": "薇儿丹蒂,瓦迪特",
                        "乐感": [
                            0,
                            0
                        ],
                        "体能": [
                            0,
                            0
                        ],
                        "表现": [
                            0,
                            0
                        ],
                        "情绪": [
                            0,
                            0
                        ],
                        "协调": [
                            0,
                            0
                        ]
                    }
                }
            }
        }
    },
    "训练室_修正者": {
        "recognition": {
            "type": "OCR",
            "param": {
                "roi": [
                    276,
                    654,
                    99,
                    46
                ],
                "expected": [
                    "正者"
                ]
            }
        },
        "action": "Click"
    },
    "进入训练室": {
        "recognition": {
            "type": "OCR",
            "param": {
                "roi": [
                    817,
                    456,
                    139,
                    74
                ],
                "expected": [
                    "训练室"
                ]
            }
        },
        "action": "Click"
    },
    "训练室_菜单": {
        "recognition": {
            "type": "OCR",
            "param": {
                "roi": [
                    40,
                    617,
                    188,
                    98
                ],
                "expected": [
                    "导航"
                ]
            }
        },
        "action": "Click"
    },
    "进入游园街_训练室": {
        "recognition": {
            "type": "OCR",
            "param": {
                "roi": [
                    965,
                    625,
                    86,
                    78
                ],
                "expected": [
                    "游园街"
                ]
            }
        },
        "action": "Click"
    }
}